pyxels/__init__.py
pyxels/pyxel.py
Pyxels-1.0.3.dist-info/METADATA
Pyxels-1.0.3.dist-info/WHEEL
Pyxels-1.0.3.dist-info/top_level.txt
Pyxels-1.0.3.dist-info/RECORD
