Metadata-Version: 2.1
Name: Pyxels
Version: 1.0.3
Summary: An API wrapper for the Python Discord Pixels API
Home-page: https://github.com/kronifer/pyxels
Author: Dillon Runke
Author-email: runkedillon@gmail.com
License: MIT
Download-URL: https://github.com/Kronifer/pyxels/archive/v1.0.0.tar.gz
Keywords: API
Platform: UNKNOWN
Classifier: Development Status :: 4 - Beta
Classifier: Intended Audience :: Developers
